efs_provider/efs_provider.py
efs_provider/manifest.toml
efs_provider/test_efs_provider.py
opsbox_efs_provider-0.1.0.dist-info/licenses/LICENCE.txt
opsbox_efs_provider-0.1.0.dist-info/METADATA
opsbox_efs_provider-0.1.0.dist-info/WHEEL
opsbox_efs_provider-0.1.0.dist-info/entry_points.txt
opsbox_efs_provider-0.1.0.dist-info/top_level.txt
opsbox_efs_provider-0.1.0.dist-info/RECORD
